{
  "now_address": "1",
  "gps_now_address": "",
  "now_province": "000000",
  "gps_province": "",
  "now_city": "000000",
  "gps_city": "",
  "now_country": "",
  "gps_country": "",
  "now_detail": "",
  "body_condition": "1",
  "body_condition_detail": "",
  "now_status": "2",
  "now_status_detail": "",
  "has_fever": "0",
  "last_touch_sars": "0",
  "last_touch_sars_date": "",
  "last_touch_sars_detail": "",
  "is_danger": "0",
  "is_goto_danger": "0",
  "jinji_lxr": "张三",
  "jinji_guanxi": "父子",
  "jiji_mobile": "18888888888",
  "other_detail": ""
}
